{"elements":[{"from":[7.428571,3.4285712,8.0],"to":[8.571428,8.0,8.0],"rotation":{"angle":0.0,"axis":"y","origin":[8.0,7.260918,8.689775]},"faces":{"south":{"uv":[2.625,12.5,2.875,13.5],"rotation":0,"texture":"#0","tintindex":0},"north":{"uv":[2.375,12.5,2.625,13.5],"rotation":0,"texture":"#0","tintindex":0},"down":{"uv":[0.25,0.0,0.0,0.0],"rotation":0,"texture":"#0","tintindex":0},"east":{"uv":[0.0,0.0,0.0,1.0],"rotation":0,"texture":"#0","tintindex":0},"west":{"uv":[0.0,0.0,0.0,1.0],"rotation":0,"texture":"#0","tintindex":0},"up":{"uv":[0.25,0.0,0.0,0.0],"rotation":0,"texture":"#0","tintindex":0}}}],"textures":{"0":"modelengine:entity/golem"},"display":{"head":{"translation":[0.0,-6.4,0.0],"scale":[4.0,4.0,4.0]}}}